<annotation>
	<folder>students</folder>
	<filename>065.jpg</filename>
	<path>E:\Neural network database\students\065.jpg</path>
	<source>
		<database>Unknown</database>
	</source>
	<size>
		<width>600</width>
		<height>400</height>
		<depth>3</depth>
	</size>
	<segmented>0</segmented>
	<object>
		<name>students</name>
		<pose>Unspecified</pose>
		<truncated>0</truncated>
		<difficult>0</difficult>
		<bndbox>
			<xmin>134</xmin>
			<ymin>52</ymin>
			<xmax>207</xmax>
			<ymax>344</ymax>
		</bndbox>
	</object>
	<object>
		<name>students</name>
		<pose>Unspecified</pose>
		<truncated>0</truncated>
		<difficult>0</difficult>
		<bndbox>
			<xmin>195</xmin>
			<ymin>74</ymin>
			<xmax>255</xmax>
			<ymax>327</ymax>
		</bndbox>
	</object>
	<object>
		<name>students</name>
		<pose>Unspecified</pose>
		<truncated>0</truncated>
		<difficult>0</difficult>
		<bndbox>
			<xmin>261</xmin>
			<ymin>47</ymin>
			<xmax>346</xmax>
			<ymax>335</ymax>
		</bndbox>
	</object>
	<object>
		<name>students</name>
		<pose>Unspecified</pose>
		<truncated>0</truncated>
		<difficult>0</difficult>
		<bndbox>
			<xmin>324</xmin>
			<ymin>53</ymin>
			<xmax>390</xmax>
			<ymax>311</ymax>
		</bndbox>
	</object>
	<object>
		<name>students</name>
		<pose>Unspecified</pose>
		<truncated>0</truncated>
		<difficult>0</difficult>
		<bndbox>
			<xmin>361</xmin>
			<ymin>65</ymin>
			<xmax>434</xmax>
			<ymax>319</ymax>
		</bndbox>
	</object>
	<object>
		<name>students</name>
		<pose>Unspecified</pose>
		<truncated>0</truncated>
		<difficult>0</difficult>
		<bndbox>
			<xmin>418</xmin>
			<ymin>48</ymin>
			<xmax>507</xmax>
			<ymax>319</ymax>
		</bndbox>
	</object>
</annotation>
